{
  "task_name": "KITCHEN_SCENE3_put_the_moka_pot_on_the_stove",
  "demo_id": "demo_30",
  "hdf5_path": "/home/tiandy/libero_100/libero_90/KITCHEN_SCENE3_put_the_moka_pot_on_the_stove_demo.hdf5",
  "bddl_path": null,
  "total_frames": 153,
  "canonical_operators": {
    "problem_name": "LIBERO_Kitchen_Tabletop_Manipulation",
    "language": "put the moka pot on the stove",
    "initial_state": {
      "On": [
        "flat_stove_1 kitchen_table_flat_stove_init_region",
        "chefmate_8_frypan_1 kitchen_table_frypan_init_region",
        "moka_pot_1 kitchen_table_moka_pot_init_region"
      ]
    },
    "goal_state": {
      "On": [
        "moka_pot_1 flat_stove_1_cook_region"
      ]
    },
    "operators": [
      {
        "name": "PickUp",
        "parameters": [
          "moka_pot_1"
        ],
        "description": "pick up the moka pot",
        "key_action": "pick up",
        "key_event": "moka pot picked up",
        "preconditions": [
          "On moka_pot_1 kitchen_table_moka_pot_init_region"
        ],
        "effects": [
          "Not On moka_pot_1 kitchen_table_moka_pot_init_region"
        ],
        "source_predicates": []
      },
      {
        "name": "Place",
        "parameters": [
          "moka_pot_1",
          "flat_stove_1"
        ],
        "description": "place the moka pot on the stove",
        "key_action": "place",
        "key_event": "moka pot placed on stove",
        "preconditions": [
          "Not On moka_pot_1 kitchen_table_moka_pot_init_region"
        ],
        "effects": [
          "On moka_pot_1 flat_stove_1_cook_region"
        ],
        "source_predicates": []
      }
    ]
  },
  "segments": [
    {
      "segment_id": "seg_1",
      "start_frame": 0,
      "end_frame": 87,
      "gripper_state": "close",
      "transition_out": "open",
      "annotation": {
        "operator": "moveto[stove]",
        "preconditions": [
          "Not On moka_pot_1 kitchen_table_moka_pot_init_region"
        ],
        "effects": [],
        "description": "The robot moves the moka pot, which it is already holding, towards the stove."
      }
    },
    {
      "segment_id": "seg_2",
      "start_frame": 88,
      "end_frame": 144,
      "gripper_state": "open",
      "transition_out": "close",
      "annotation": {
        "operator": "moveto[moka pot]",
        "preconditions": [
          "On moka_pot_1 kitchen_table_moka_pot_init_region",
          "gripper_open"
        ],
        "effects": [],
        "description": "The robot moves its arm to hover over the moka pot."
      }
    },
    {
      "segment_id": "seg_3",
      "start_frame": 145,
      "end_frame": 152,
      "gripper_state": "close",
      "transition_out": null,
      "annotation": {
        "operator": "Place[moka pot, stove]",
        "preconditions": [
          "Not On moka_pot_1 kitchen_table_moka_pot_init_region"
        ],
        "effects": [
          "On moka_pot_1 flat_stove_1_cook_region"
        ],
        "description": "The robot moves the moka pot, which it is holding, onto the stove."
      }
    }
  ]
}