{
  "task_name": "KITCHEN_SCENE6_close_the_microwave",
  "demo_id": "demo_22",
  "hdf5_path": "/home/tiandy/libero_100/libero_90/KITCHEN_SCENE6_close_the_microwave_demo.hdf5",
  "bddl_path": null,
  "total_frames": 209,
  "canonical_operators": {
    "problem_name": "LIBERO_Kitchen_Tabletop_Manipulation",
    "language": "close the microwave",
    "initial_state": {
      "On": [
        "porcelain_mug_1 kitchen_table_porcelain_mug_init_region",
        "white_yellow_mug_1 kitchen_table_white_yellow_mug_init_region",
        "microwave_1 kitchen_table_microwave_init_region"
      ],
      "Open": [
        "microwave_1"
      ]
    },
    "goal_state": {
      "Close": [
        "microwave_1"
      ]
    },
    "operators": [
      {
        "name": "Close",
        "parameters": [
          "microwave"
        ],
        "description": "close the microwave",
        "key_action": "close",
        "key_event": "microwave closed",
        "preconditions": [
          "Open microwave"
        ],
        "effects": [
          "Close microwave"
        ],
        "source_predicates": []
      }
    ]
  },
  "segments": [
    {
      "segment_id": "seg_1",
      "start_frame": 0,
      "end_frame": 51,
      "gripper_state": "close",
      "transition_out": "open",
      "annotation": {
        "operator": "Close[microwave]",
        "preconditions": [
          "Open microwave"
        ],
        "effects": [
          "-Open microwave",
          "Close microwave"
        ],
        "description": "The robot arm moves towards the open microwave door and pushes it closed."
      }
    },
    {
      "segment_id": "seg_2",
      "start_frame": 52,
      "end_frame": 109,
      "gripper_state": "open",
      "transition_out": "close",
      "annotation": {
        "operator": "Close[microwave]",
        "preconditions": [
          "Open microwave"
        ],
        "effects": [
          "Close microwave",
          "-Open microwave"
        ],
        "description": "The robot arm moves to the microwave door and pushes it to close the microwave."
      }
    },
    {
      "segment_id": "seg_3",
      "start_frame": 110,
      "end_frame": 208,
      "gripper_state": "close",
      "transition_out": null,
      "annotation": {
        "operator": "Close[microwave]",
        "preconditions": [
          "Open microwave"
        ],
        "effects": [
          "Close microwave"
        ],
        "description": "The robot arm moves to the microwave door and pushes it shut, closing the microwave."
      }
    }
  ]
}